integration_tests/__init__.py
integration_tests/conftest.py
integration_tests/utils.py
integration_tests/endpoints/__init__.py
integration_tests/endpoints/test_anomaly_detection.py
integration_tests/endpoints/test_datasets.py
integration_tests/endpoints/test_experiments.py
integration_tests/endpoints/test_forecasting.py
integration_tests/endpoints/test_licenses.py
integration_tests/endpoints/test_use_cases.py
integration_tests/endpoints/test_user_groups.py
integration_tests/endpoints/test_users.py
integration_tests/endpoints/test_workspaces.py
integration_tests/extended_functions/__init__.py
integration_tests/extended_functions/test_extended_anomaly_detection.py
integration_tests/extended_functions/test_extended_datasets.py
integration_tests/extended_functions/test_extended_forecasting.py
tim/__init__.py
tim/_version.py
tim/client.py
tim/core/__init__.py
tim/core/api.py
tim/core/authentication.py
tim/core/credentials.py
tim/core/helper.py
tim/core/server.py
tim/core/types.py
tim/endpoints/__init__.py
tim/endpoints/anomaly_detection.py
tim/endpoints/datasets.py
tim/endpoints/experiments.py
tim/endpoints/forecasting.py
tim/endpoints/licenses.py
tim/endpoints/telemetry.py
tim/endpoints/use_cases.py
tim/endpoints/user_groups.py
tim/endpoints/users.py
tim/endpoints/workspaces.py
tim/extended_functions/__init__.py
tim/extended_functions/extended_anomaly_detection.py
tim/extended_functions/extended_datasets.py
tim/extended_functions/extended_forecasting.py
tim/helper_functions/__init__.py
tim/helper_functions/helper_post_process.py
tim_client-5.3.0.dist-info/LICENSE
tim_client-5.3.0.dist-info/METADATA
tim_client-5.3.0.dist-info/WHEEL
tim_client-5.3.0.dist-info/top_level.txt
tim_client-5.3.0.dist-info/RECORD
