Metadata-Version: 2.1
Name: tim-client
Version: 5.3.0
Summary: TIM Python Client
Home-page: https://tangent.works
Author: Tangent Works
Author-email: info@tangent.works
Project-URL: Documentation, https://docs.tangent.works/
Classifier: Programming Language :: Python :: 3
Classifier: License :: OSI Approved :: MIT License
Classifier: Operating System :: OS Independent
Requires-Python: >=3.6
License-File: LICENSE
Requires-Dist: requests
Requires-Dist: pandas
Requires-Dist: typing-extensions
Provides-Extra: dev
Requires-Dist: pre-commit ; extra == 'dev'
Requires-Dist: pytest ; extra == 'dev'
Requires-Dist: pytest-dotenv ; extra == 'dev'
Requires-Dist: requests-mock ; extra == 'dev'
Requires-Dist: jsonschema ; extra == 'dev'
Provides-Extra: pipeline
Requires-Dist: build ; extra == 'pipeline'
Requires-Dist: pytest-cov ; extra == 'pipeline'
Requires-Dist: pytest-azurepipelines ; extra == 'pipeline'
Requires-Dist: pytest-xdist[psutil] ; extra == 'pipeline'
